{"type":"record","name":"sensor_raw","namespace":"com.trivadis","doc":"This is the sensor-raw value schema","fields":[{"name":"_id","type":"string"},{"name":"createdAt","type":"long","logicalType":"timestamp-millis"},{"name":"currentLocation","type":{"type":"record","name":"currentLocation","fields":[{"name":"coordinates","type":{"type":"array","items":"float"}},{"name":"timestamp","type":"long","logicalType":"timestamp-millis"},{"name":"type","type":"string"}]}},{"name":"exposure","type":"string"},{"name":"grouptag","type":"string"},{"name":"lastMeasurementAt","type":"long","logicalType":"timestamp-millis"},{"name":"loc","type":{"type":"array","items":{"type":"record","name":"loc_record","fields":[{"name":"geometry","type":{"type":"record","name":"geometry","fields":[{"name":"coordinates","type":{"type":"array","items":"float"}},{"name":"timestamp","type":"long","logicalType":"timestamp-millis"},{"name":"type","type":"string"}]}},{"name":"type","type":"string"}]}}},{"name":"model","type":"string"},{"name":"name","type":"string"},{"name":"sensors","type":{"type":"array","items":{"type":"record","name":"sensors_record","fields":[{"name":"_id","type":"string"},{"name":"icon","type":"string"},{"name":"lastMeasurement","type":{"type":"record","name":"lastMeasurement","fields":[{"name":"createdAt","type":"long","logicalType":"timestamp-millis"},{"name":"value","type":"string"}]}},{"name":"sensorType","type":"string"},{"name":"title","type":"string"},{"name":"unit","type":"string"}]}}},{"name":"uptimestamp_millisdAt","type":"long","logicalType":"timestamp-millis"}]}